README.md
setup.py
social_auth_ragtag_id/__init__.py
social_auth_ragtag_id/backends.py
social_auth_ragtag_id.egg-info/PKG-INFO
social_auth_ragtag_id.egg-info/SOURCES.txt
social_auth_ragtag_id.egg-info/dependency_links.txt
social_auth_ragtag_id.egg-info/requires.txt
social_auth_ragtag_id.egg-info/top_level.txt